LICENSE
certbot_dns_corenetworks/__init__.py
certbot_dns_corenetworks/dns_corenetworks.py
certbot_dns_corenetworks/test/__init__.py
certbot_dns_corenetworks/test/unit/__init__.py
certbot_dns_corenetworks/test/unit/test_dns_corenetwork.py
certbot_dns_corenetworks-0.2.1.dist-info/entry_points.txt
certbot_dns_corenetworks-0.2.1.dist-info/LICENSE
certbot_dns_corenetworks-0.2.1.dist-info/WHEEL
certbot_dns_corenetworks-0.2.1.dist-info/METADATA
certbot_dns_corenetworks-0.2.1.dist-info/RECORD
