Metadata-Version: 2.1
Name: certbot-dns-corenetworks
Version: 0.2.1
Summary: Core Networks DNS Authenticator plugin for Certbot.
Home-page: https://github.com/thegeeklab/certbot-dns-corenetworks/
License: MIT
Keywords: dns,certbot,automation,corenetworks
Author: Robert Kaussow
Author-email: mail@thegeeklab.de
Requires-Python: >=3.6.0,<4.0.0
Classifier: Development Status :: 5 - Production/Stable
Classifier: Environment :: Plugins
Classifier: Intended Audience :: Developers
Classifier: Intended Audience :: System Administrators
Classifier: License :: OSI Approved :: MIT License
Classifier: Natural Language :: English
Classifier: Operating System :: POSIX
Classifier: Programming Language :: Python :: 3
Classifier: Programming Language :: Python :: 3.6
Classifier: Programming Language :: Python :: 3.7
Classifier: Programming Language :: Python :: 3.8
Classifier: Programming Language :: Python :: 3.9
Classifier: Topic :: Security
Classifier: Topic :: System :: Networking
Classifier: Topic :: Utilities
Requires-Dist: acme (>=1.10.1,<2.0.0)
Requires-Dist: certbot (>=1.10.1,<2.0.0)
Requires-Dist: corenetworks (>=0.2.0,<0.3.0)
Requires-Dist: parsedatetime (>=2.6,<3.0)
Requires-Dist: zope.interface (>=5.2.0,<6.0.0)
Project-URL: Documentation, https://github.com/thegeeklab/certbot-dns-corenetworks/
Project-URL: Repository, https://github.com/thegeeklab/certbot-dns-corenetworks/
